<?xml version="1.0" encoding="utf-8" ?>
<field name="test_random_control_field" type="control_field" dimensions="3" number_of_elements="64">
    <value cell_id="1">4.668376,-5.322942,5.219865</value>
    <value cell_id="2">7.717917,-8.311556,3.936254</value>
    <value cell_id="3">7.649474,-8.474116,-3.758971</value>
    <value cell_id="4">4.643820,-5.420754,-5.255843</value>
    <value cell_id="5">7.873634,-3.789013,8.118757</value>
    <value cell_id="6">13.871951,-6.436168,6.899396</value>
    <value cell_id="7">13.608532,-6.796968,-6.969347</value>
    <value cell_id="8">7.808911,-3.907302,-8.553318</value>
    <value cell_id="9">8.236450,3.882585,7.469250</value>
    <value cell_id="10">14.483185,7.234397,5.575670</value>
    <value cell_id="11">14.777623,7.502759,-8.225623</value>
    <value cell_id="12">8.348557,4.015974,-9.224535</value>
    <value cell_id="13">5.075542,5.215448,4.417915</value>
    <value cell_id="14">8.365995,8.452803,2.628289</value>
    <value cell_id="15">8.491350,8.580141,-5.053393</value>
    <value cell_id="16">5.161704,5.311281,-6.071634</value>
    <value cell_id="17">2.936889,-8.582445,8.513048</value>
    <value cell_id="18">6.116933,-14.005596,7.477022</value>
    <value cell_id="19">5.905820,-14.422698,-6.406200</value>
    <value cell_id="20">2.890631,-8.761199,-8.173418</value>
    <value cell_id="21">6.298006,-6.888928,14.160888</value>
    <value cell_id="22">16.502293,-13.653722,17.154124</value>
    <value cell_id="23">14.838313,-15.318476,-14.517755</value>
    <value cell_id="24">6.076437,-7.121028,-13.972206</value>
    <value cell_id="25">7.041935,6.824666,12.966037</value>
    <value cell_id="26">18.131327,16.029086,13.367461</value>
    <value cell_id="27">19.170051,17.391969,-17.303851</value>
    <value cell_id="28">7.232676,7.208383,-15.210562</value>
    <value cell_id="29">3.556357,8.172770,7.270058</value>
    <value cell_id="30">7.110970,14.095207,5.296489</value>
    <value cell_id="31">7.360924,14.451442,-8.463671</value>
    <value cell_id="32">3.699816,8.358204,-9.435698</value>
    <value cell_id="33">-5.367376,-9.213579,8.667029</value>
    <value cell_id="34">-8.870903,-15.256488,7.658255</value>
    <value cell_id="35">-8.700211,-15.669013,-6.265649</value>
    <value cell_id="36">-5.261019,-9.418192,-8.085172</value>
    <value cell_id="37">-8.680097,-8.047932,14.440155</value>
    <value cell_id="38">-17.576687,-17.123938,17.067567</value>
    <value cell_id="39">-16.735408,-19.019960,-14.220661</value>
    <value cell_id="40">-8.452438,-8.441774,-13.889654</value>
    <value cell_id="41">-8.550929,6.094626,13.616235</value>
    <value cell_id="42">-17.901939,14.755724,15.918249</value>
    <value cell_id="43">-16.972602,16.597116,-17.395446</value>
    <value cell_id="44">-8.168408,6.434188,-15.035628</value>
    <value cell_id="45">-4.976166,7.748703,7.575160</value>
    <value cell_id="46">-8.336972,13.364587,5.957807</value>
    <value cell_id="47">-7.967314,13.788502,-8.290473</value>
    <value cell_id="48">-4.751364,7.929231,-9.315777</value>
    <value cell_id="49">-6.553264,-6.057494,5.438023</value>
    <value cell_id="50">-10.096582,-9.493484,4.250808</value>
    <value cell_id="51">-10.034861,-9.650604,-3.477176</value>
    <value cell_id="52">-6.485324,-6.164281,-5.089264</value>
    <value cell_id="53">-10.000422,-4.928396,8.479287</value>
    <value cell_id="54">-16.109975,-8.371280,7.401569</value>
    <value cell_id="55">-16.022494,-8.739642,-6.492718</value>
    <value cell_id="56">-9.884959,-5.078592,-8.295334</value>
    <value cell_id="57">-9.893717,2.923043,7.981033</value>
    <value cell_id="58">-16.033058,5.726908,6.510476</value>
    <value cell_id="59">-15.766550,6.121336,-7.690474</value>
    <value cell_id="60">-9.690050,3.060725,-8.926277</value>
    <value cell_id="61">-6.315850,4.616097,4.734762</value>
    <value cell_id="62">-9.752718,7.521294,3.144354</value>
    <value cell_id="63">-9.600027,7.682070,-4.700909</value>
    <value cell_id="64">-6.181959,4.714971,-5.865632</value>
</field>
