<?xml version="1.0" encoding="utf-8" ?>
<field name="test_random_control_field" type="control_field" dimensions="3" number_of_elements="216">
    <value cell_id="1">0.000000,0.000000,0.000000</value>
    <value cell_id="2">0.000000,0.000000,0.000000</value>
    <value cell_id="3">0.000000,0.000000,0.000000</value>
    <value cell_id="4">0.000000,0.000000,0.000000</value>
    <value cell_id="5">0.000000,0.000000,0.000000</value>
    <value cell_id="6">0.000000,0.000000,0.000000</value>
    <value cell_id="7">0.000000,0.000000,0.000000</value>
    <value cell_id="8">0.000000,0.000000,0.000000</value>
    <value cell_id="9">0.000000,0.000000,0.000000</value>
    <value cell_id="10">0.000000,0.000000,0.000000</value>
    <value cell_id="11">0.000000,0.000000,0.000000</value>
    <value cell_id="12">0.000000,0.000000,0.000000</value>
    <value cell_id="13">0.000000,0.000000,0.000000</value>
    <value cell_id="14">0.000000,0.000000,0.000000</value>
    <value cell_id="15">0.000000,0.000000,0.000000</value>
    <value cell_id="16">0.000000,0.000000,0.000000</value>
    <value cell_id="17">0.000000,0.000000,0.000000</value>
    <value cell_id="18">0.000000,0.000000,0.000000</value>
    <value cell_id="19">0.000000,0.000000,0.000000</value>
    <value cell_id="20">0.000000,0.000000,0.000000</value>
    <value cell_id="21">0.000000,0.000000,0.000000</value>
    <value cell_id="22">0.000000,0.000000,0.000000</value>
    <value cell_id="23">0.000000,0.000000,0.000000</value>
    <value cell_id="24">0.000000,0.000000,0.000000</value>
    <value cell_id="25">0.000000,0.000000,0.000000</value>
    <value cell_id="26">0.000000,0.000000,0.000000</value>
    <value cell_id="27">0.000000,0.000000,0.000000</value>
    <value cell_id="28">0.000000,0.000000,0.000000</value>
    <value cell_id="29">0.000000,0.000000,0.000000</value>
    <value cell_id="30">0.000000,0.000000,0.000000</value>
    <value cell_id="31">0.000000,0.000000,0.000000</value>
    <value cell_id="32">0.000000,0.000000,0.000000</value>
    <value cell_id="33">0.000000,0.000000,0.000000</value>
    <value cell_id="34">0.000000,0.000000,0.000000</value>
    <value cell_id="35">0.000000,0.000000,0.000000</value>
    <value cell_id="36">0.000000,0.000000,0.000000</value>
    <value cell_id="37">0.000000,0.000000,0.000000</value>
    <value cell_id="38">0.000000,0.000000,0.000000</value>
    <value cell_id="39">0.000000,0.000000,0.000000</value>
    <value cell_id="40">0.000000,0.000000,0.000000</value>
    <value cell_id="41">0.000000,0.000000,0.000000</value>
    <value cell_id="42">0.000000,0.000000,0.000000</value>
    <value cell_id="43">0.000000,0.000000,0.000000</value>
    <value cell_id="44">0.000000,0.000000,0.000000</value>
    <value cell_id="45">0.000000,0.000000,0.000000</value>
    <value cell_id="46">0.000000,0.000000,0.000000</value>
    <value cell_id="47">0.000000,0.000000,0.000000</value>
    <value cell_id="48">0.000000,0.000000,0.000000</value>
    <value cell_id="49">0.000000,0.000000,0.000000</value>
    <value cell_id="50">0.000000,0.000000,0.000000</value>
    <value cell_id="51">0.000000,0.000000,0.000000</value>
    <value cell_id="52">0.000000,0.000000,0.000000</value>
    <value cell_id="53">0.000000,0.000000,0.000000</value>
    <value cell_id="54">0.000000,0.000000,0.000000</value>
    <value cell_id="55">0.000000,0.000000,0.000000</value>
    <value cell_id="56">0.000000,0.000000,0.000000</value>
    <value cell_id="57">0.000000,0.000000,0.000000</value>
    <value cell_id="58">0.000000,0.000000,0.000000</value>
    <value cell_id="59">0.000000,0.000000,0.000000</value>
    <value cell_id="60">0.000000,0.000000,0.000000</value>
    <value cell_id="61">0.000000,0.000000,0.000000</value>
    <value cell_id="62">0.000000,0.000000,0.000000</value>
    <value cell_id="63">0.000000,0.000000,0.000000</value>
    <value cell_id="64">0.000000,0.000000,0.000000</value>
    <value cell_id="65">0.000000,0.000000,0.000000</value>
    <value cell_id="66">0.000000,0.000000,0.000000</value>
    <value cell_id="67">0.000000,0.000000,0.000000</value>
    <value cell_id="68">0.000000,0.000000,0.000000</value>
    <value cell_id="69">0.000000,0.000000,0.000000</value>
    <value cell_id="70">0.000000,0.000000,0.000000</value>
    <value cell_id="71">0.000000,0.000000,0.000000</value>
    <value cell_id="72">0.000000,0.000000,0.000000</value>
    <value cell_id="73">0.444140,-0.670632,0.066026</value>
    <value cell_id="74">-0.205736,2.085824,3.810367</value>
    <value cell_id="75">-0.752954,6.220958,4.927597</value>
    <value cell_id="76">0.923791,5.782847,1.158505</value>
    <value cell_id="77">-3.301885,4.523937,-0.890981</value>
    <value cell_id="78">-2.252426,2.451660,-1.351125</value>
    <value cell_id="79">0.981995,-2.968937,-2.750217</value>
    <value cell_id="80">-2.288628,-4.469663,2.400139</value>
    <value cell_id="81">-13.085279,9.616971,13.311362</value>
    <value cell_id="82">-9.590338,10.069661,1.792347</value>
    <value cell_id="83">-7.971583,6.381092,-2.497364</value>
    <value cell_id="84">-4.509459,3.035771,-0.593933</value>
    <value cell_id="85">-3.990548,-6.854612,-6.668950</value>
    <value cell_id="86">-9.327767,-12.408995,-6.535608</value>
    <value cell_id="87">-18.115423,1.789116,17.809136</value>
    <value cell_id="88">-8.346865,-9.516198,1.504025</value>
    <value cell_id="89">-11.264574,-4.860230,-4.020502</value>
    <value cell_id="90">-10.395853,-1.626273,-0.575037</value>
    <value cell_id="91">-6.528341,-4.198265,-1.624574</value>
    <value cell_id="92">-19.134083,-2.373520,0.454672</value>
    <value cell_id="93">-28.141564,3.129448,16.401197</value>
    <value cell_id="94">-41.492065,-2.488887,5.399290</value>
    <value cell_id="95">-24.036961,-1.570967,-0.204127</value>
    <value cell_id="96">-10.127565,-0.906850,-0.408576</value>
    <value cell_id="97">-3.321809,-0.494583,-1.177099</value>
    <value cell_id="98">-10.737561,-0.328093,4.040082</value>
    <value cell_id="99">-26.259603,-3.212283,12.295532</value>
    <value cell_id="100">-38.898267,1.082769,5.299400</value>
    <value cell_id="101">-26.280654,2.438659,4.107233</value>
    <value cell_id="102">-9.165896,1.284680,-0.105196</value>
    <value cell_id="103">0.122370,-1.691427,1.018484</value>
    <value cell_id="104">-2.924741,-2.700461,2.141138</value>
    <value cell_id="105">-11.729113,-1.419358,4.303458</value>
    <value cell_id="106">-16.711450,0.621015,3.353602</value>
    <value cell_id="107">-15.423826,1.999116,2.041830</value>
    <value cell_id="108">-6.022719,1.316204,1.189772</value>
    <value cell_id="109">-0.568707,-0.436431,0.355391</value>
    <value cell_id="110">-1.608207,2.177472,2.890187</value>
    <value cell_id="111">-1.020261,5.105578,3.987886</value>
    <value cell_id="112">-0.331645,6.078438,0.797009</value>
    <value cell_id="113">-1.525108,3.192957,0.031082</value>
    <value cell_id="114">-1.315949,1.679781,-0.453168</value>
    <value cell_id="115">-2.127752,-0.256020,-0.737127</value>
    <value cell_id="116">-5.484207,1.888211,4.062815</value>
    <value cell_id="117">-7.907357,7.566522,9.117672</value>
    <value cell_id="118">-6.632870,7.619394,1.706874</value>
    <value cell_id="119">-5.578887,2.402498,-1.085784</value>
    <value cell_id="120">-4.242440,2.205054,-0.584723</value>
    <value cell_id="121">-3.558263,-1.543262,-2.785394</value>
    <value cell_id="122">-10.483100,-1.170612,0.456689</value>
    <value cell_id="123">-16.498818,2.492217,8.922085</value>
    <value cell_id="124">-16.354022,-0.291725,0.374246</value>
    <value cell_id="125">-13.510963,-6.372627,-3.423239</value>
    <value cell_id="126">-7.262461,-1.959318,0.339869</value>
    <value cell_id="127">-6.037627,-1.374449,-1.819781</value>
    <value cell_id="128">-16.239085,0.302067,1.645594</value>
    <value cell_id="129">-24.587306,1.171593,10.264154</value>
    <value cell_id="130">-25.788008,-1.937797,3.236139</value>
    <value cell_id="131">-19.429906,-2.354761,-2.378496</value>
    <value cell_id="132">-7.559183,-1.940990,-0.458952</value>
    <value cell_id="133">-3.155796,-0.489194,-0.206386</value>
    <value cell_id="134">-11.910560,-1.988618,2.849670</value>
    <value cell_id="135">-25.644020,-1.662940,6.280882</value>
    <value cell_id="136">-24.572457,-2.701265,4.530802</value>
    <value cell_id="137">-15.639182,-0.978314,-0.509856</value>
    <value cell_id="138">-5.203188,-0.711799,-0.339177</value>
    <value cell_id="139">-1.018305,-0.711777,0.419054</value>
    <value cell_id="140">-4.525129,-1.995563,1.360350</value>
    <value cell_id="141">-11.004848,-0.965334,3.121875</value>
    <value cell_id="142">-11.294282,0.311090,2.610799</value>
    <value cell_id="143">-8.479971,0.893475,1.724434</value>
    <value cell_id="144">-3.610213,0.633202,1.113246</value>
    <value cell_id="145">0.000000,0.000000,0.000000</value>
    <value cell_id="146">0.000000,0.000000,0.000000</value>
    <value cell_id="147">0.000000,0.000000,0.000000</value>
    <value cell_id="148">0.000000,0.000000,0.000000</value>
    <value cell_id="149">0.000000,0.000000,0.000000</value>
    <value cell_id="150">0.000000,0.000000,0.000000</value>
    <value cell_id="151">0.000000,0.000000,0.000000</value>
    <value cell_id="152">0.000000,0.000000,0.000000</value>
    <value cell_id="153">0.000000,0.000000,0.000000</value>
    <value cell_id="154">0.000000,0.000000,0.000000</value>
    <value cell_id="155">0.000000,0.000000,0.000000</value>
    <value cell_id="156">0.000000,0.000000,0.000000</value>
    <value cell_id="157">0.000000,0.000000,0.000000</value>
    <value cell_id="158">0.000000,0.000000,0.000000</value>
    <value cell_id="159">0.000000,0.000000,0.000000</value>
    <value cell_id="160">0.000000,0.000000,0.000000</value>
    <value cell_id="161">0.000000,0.000000,0.000000</value>
    <value cell_id="162">0.000000,0.000000,0.000000</value>
    <value cell_id="163">0.000000,0.000000,0.000000</value>
    <value cell_id="164">0.000000,0.000000,0.000000</value>
    <value cell_id="165">0.000000,0.000000,0.000000</value>
    <value cell_id="166">0.000000,0.000000,0.000000</value>
    <value cell_id="167">0.000000,0.000000,0.000000</value>
    <value cell_id="168">0.000000,0.000000,0.000000</value>
    <value cell_id="169">0.000000,0.000000,0.000000</value>
    <value cell_id="170">0.000000,0.000000,0.000000</value>
    <value cell_id="171">0.000000,0.000000,0.000000</value>
    <value cell_id="172">0.000000,0.000000,0.000000</value>
    <value cell_id="173">0.000000,0.000000,0.000000</value>
    <value cell_id="174">0.000000,0.000000,0.000000</value>
    <value cell_id="175">0.000000,0.000000,0.000000</value>
    <value cell_id="176">0.000000,0.000000,0.000000</value>
    <value cell_id="177">0.000000,0.000000,0.000000</value>
    <value cell_id="178">0.000000,0.000000,0.000000</value>
    <value cell_id="179">0.000000,0.000000,0.000000</value>
    <value cell_id="180">0.000000,0.000000,0.000000</value>
    <value cell_id="181">0.000000,0.000000,0.000000</value>
    <value cell_id="182">0.000000,0.000000,0.000000</value>
    <value cell_id="183">0.000000,0.000000,0.000000</value>
    <value cell_id="184">0.000000,0.000000,0.000000</value>
    <value cell_id="185">0.000000,0.000000,0.000000</value>
    <value cell_id="186">0.000000,0.000000,0.000000</value>
    <value cell_id="187">0.000000,0.000000,0.000000</value>
    <value cell_id="188">0.000000,0.000000,0.000000</value>
    <value cell_id="189">0.000000,0.000000,0.000000</value>
    <value cell_id="190">0.000000,0.000000,0.000000</value>
    <value cell_id="191">0.000000,0.000000,0.000000</value>
    <value cell_id="192">0.000000,0.000000,0.000000</value>
    <value cell_id="193">0.000000,0.000000,0.000000</value>
    <value cell_id="194">0.000000,0.000000,0.000000</value>
    <value cell_id="195">0.000000,0.000000,0.000000</value>
    <value cell_id="196">0.000000,0.000000,0.000000</value>
    <value cell_id="197">0.000000,0.000000,0.000000</value>
    <value cell_id="198">0.000000,0.000000,0.000000</value>
    <value cell_id="199">0.000000,0.000000,0.000000</value>
    <value cell_id="200">0.000000,0.000000,0.000000</value>
    <value cell_id="201">0.000000,0.000000,0.000000</value>
    <value cell_id="202">0.000000,0.000000,0.000000</value>
    <value cell_id="203">0.000000,0.000000,0.000000</value>
    <value cell_id="204">0.000000,0.000000,0.000000</value>
    <value cell_id="205">0.000000,0.000000,0.000000</value>
    <value cell_id="206">0.000000,0.000000,0.000000</value>
    <value cell_id="207">0.000000,0.000000,0.000000</value>
    <value cell_id="208">0.000000,0.000000,0.000000</value>
    <value cell_id="209">0.000000,0.000000,0.000000</value>
    <value cell_id="210">0.000000,0.000000,0.000000</value>
    <value cell_id="211">0.000000,0.000000,0.000000</value>
    <value cell_id="212">0.000000,0.000000,0.000000</value>
    <value cell_id="213">0.000000,0.000000,0.000000</value>
    <value cell_id="214">0.000000,0.000000,0.000000</value>
    <value cell_id="215">0.000000,0.000000,0.000000</value>
    <value cell_id="216">0.000000,0.000000,0.000000</value>
</field>
