<field name="interpolated_control_field" type="electric_field" dimensions="3" number_of_elements="125">
<value node_number="1">0.0,0.0,0.0</value>
<value node_number="2">0.0,0.0,0.0</value>
<value node_number="3">0.0,0.0,0.0</value>
<value node_number="4">0.0,0.0,0.0</value>
<value node_number="5">0.0,0.0,0.0</value>
<value node_number="6">0.0,0.0,0.0</value>
<value node_number="7">0.0,0.0,0.0</value>
<value node_number="8">0.0,0.0,0.0</value>
<value node_number="9">-0.1494675,0.2752825,-0.0373565</value>
<value node_number="10">-0.30786199999999997,0.48012849999999996,0.018069999999999996</value>
<value node_number="11">-0.1583945,0.204846,0.0554265</value>
<value node_number="12">0.0,0.0,0.0</value>
<value node_number="13">0.0,0.0,0.0</value>
<value node_number="14">0.0,0.0,0.0</value>
<value node_number="15">-0.1601975,0.1764025,0.0615485</value>
<value node_number="16">-0.30953699999999995,0.38110999999999995,0.047677</value>
<value node_number="17">-0.1493395,0.2047075,-0.0138715</value>
<value node_number="18">0.0,0.0,0.0</value>
<value node_number="19">0.0,0.0,0.0</value>
<value node_number="20">0.0,0.0,0.0</value>
<value node_number="21">-0.146568,0.1553405,0.1812245</value>
<value node_number="22">-0.31047800000000003,0.31340599999999996,0.354483</value>
<value node_number="23">-0.16391,0.1580655,0.1732585</value>
<value node_number="24">0.0,0.0,0.0</value>
<value node_number="25">0.0,0.0,0.0</value>
<value node_number="26">0.0,0.0,0.0</value>
<value node_number="27">-0.1652065,0.1110305,0.198991</value>
<value node_number="28">-0.305111,0.166624,0.4331215</value>
<value node_number="29">-0.1399045,0.0555935,0.2341305</value>
<value node_number="30">0.0,0.0,0.0</value>
<value node_number="31">0.0,0.0,0.0</value>
<value node_number="32">0.0,0.0,0.0</value>
<value node_number="33">0.0,0.0,0.0</value>
<value node_number="34">0.0,0.0,0.0</value>
<value node_number="35">0.0,0.0,0.0</value>
<value node_number="36">0.0,0.0,0.0</value>
<value node_number="37">0.0,0.0,0.0</value>
<value node_number="38">0.0,0.0,0.0</value>
<value node_number="39">0.0,0.0,0.0</value>
<value node_number="40">0.0,0.0,0.0</value>
<value node_number="41">0.0,0.0,0.0</value>
<value node_number="42">0.0,0.0,0.0</value>
<value node_number="43">0.0,0.0,0.0</value>
<value node_number="44">0.0,0.0,0.0</value>
<value node_number="45">-0.202893,0.18954949999999998,-0.02051125</value>
<value node_number="46">-0.2467995,0.19183675,-0.0327045</value>
<value node_number="47">-0.19330999999999998,0.24228224999999998,-0.03780725</value>
<value node_number="48">-0.40577525,0.3831565,0.05687924999999999</value>
<value node_number="49">-0.489203,0.41258150000000005,0.058313250000000004</value>
<value node_number="50">-0.39212725,0.46004425,0.034307500000000005</value>
<value node_number="51">-0.20288225,0.193607,0.0773905</value>
<value node_number="52">-0.2424035,0.22074475,0.09101775000000001</value>
<value node_number="53">-0.19881725,0.217762,0.07211475</value>
<value node_number="54">-0.17653200000000002,0.16671049999999998,0.235415</value>
<value node_number="55">-0.2153805,0.134164,0.3102365</value>
<value node_number="56">-0.18208475,0.0729205,0.282499</value>
<value node_number="57">-0.377738,0.34661699999999995,0.454444</value>
<value node_number="58">-0.45761925000000003,0.31772925,0.58477875</value>
<value node_number="59">-0.38767575,0.21112725000000002,0.5241370000000001</value>
<value node_number="60">-0.201206,0.1799065,0.21902900000000003</value>
<value node_number="61">-0.24223875,0.18356525,0.27454225</value>
<value node_number="62">-0.20559100000000002,0.13820675,0.24163800000000002</value>
<value node_number="63">-0.182938,0.3021335,0.016903</value>
<value node_number="64">-0.2071575,0.29269924999999997,0.16337325</value>
<value node_number="65">-0.17223725,0.20587724999999998,0.21840425</value>
<value node_number="66">-0.38077099999999997,0.5413445,0.119112</value>
<value node_number="67">-0.44562625,0.5544315,0.35281025</value>
<value node_number="68">-0.37402525,0.40985425,0.41997474999999995</value>
<value node_number="69">-0.19783299999999998,0.239211,0.102209</value>
<value node_number="70">-0.23846875,0.26173225,0.189437</value>
<value node_number="71">-0.201788,0.20397700000000002,0.20157049999999999</value>
<value node_number="72">0.0,0.0,0.0</value>
<value node_number="73">0.0,0.0,0.0</value>
<value node_number="74">0.0,0.0,0.0</value>
<value node_number="75">0.0,0.0,0.0</value>
<value node_number="76">0.0,0.0,0.0</value>
<value node_number="77">0.0,0.0,0.0</value>
<value node_number="78">0.0,0.0,0.0</value>
<value node_number="79">0.0,0.0,0.0</value>
<value node_number="80">0.0,0.0,0.0</value>
<value node_number="81">-0.204297,0.205826,0.1101095</value>
<value node_number="82">-0.24680575,0.21798725,0.198267</value>
<value node_number="83">-0.20521075,0.15587774999999998,0.21842725000000002</value>
<value node_number="84">-0.3933005,0.42674425,0.150311</value>
<value node_number="85">-0.47050025,0.42179200000000006,0.3723355</value>
<value node_number="86">-0.38452375,0.26891475,0.46242375</value>
<value node_number="87">-0.1890035,0.22091824999999998,0.0402015</value>
<value node_number="88">-0.22369450000000002,0.20380475,0.1740685</value>
<value node_number="89">-0.179313,0.113037,0.2439965</value>
<value node_number="90">0.0,0.0,0.0</value>
<value node_number="91">0.0,0.0,0.0</value>
<value node_number="92">0.0,0.0,0.0</value>
<value node_number="93">0.0,0.0,0.0</value>
<value node_number="94">0.0,0.0,0.0</value>
<value node_number="95">0.0,0.0,0.0</value>
<value node_number="96">0.0,0.0,0.0</value>
<value node_number="97">0.0,0.0,0.0</value>
<value node_number="98">0.0,0.0,0.0</value>
<value node_number="99">-0.250894,0.210452,0.044380125</value>
<value node_number="100">-0.289201375,0.19918575000000002,0.22055087499999998</value>
<value node_number="101">-0.23079624999999998,0.11996875,0.30716462499999997</value>
<value node_number="102">-0.311520375,0.224459625,0.053742374999999995</value>
<value node_number="103">-0.362837875,0.2281845,0.272155125</value>
<value node_number="104">-0.28240750000000003,0.16672525,0.35717875</value>
<value node_number="105">-0.246597125,0.2755335,0.037914500000000004</value>
<value node_number="106">-0.2890625,0.27725075,0.220325125</value>
<value node_number="107">-0.227386375,0.20621362499999998,0.28121450000000003</value>
<value node_number="108">-0.50860075,0.43960449999999995,0.180715375</value>
<value node_number="109">-0.5987936249999999,0.44896387500000007,0.46828662499999996</value>
<value node_number="110">-0.486918375,0.30650125,0.578079375</value>
<value node_number="111">-0.619269,0.4899165,0.21439149999999998</value>
<value node_number="112">-0.7325976249999999,0.5257585,0.56523075</value>
<value node_number="113">-0.58673975,0.40099737500000004,0.67238525</value>
<value node_number="114">-0.49770400000000004,0.534356375,0.16838762500000004</value>
<value node_number="115">-0.5918672500000001,0.564906375,0.45951699999999995</value>
<value node_number="116">-0.479095875,0.43388062499999996,0.535505125</value>
<value node_number="117">-0.25770675,0.2291525,0.13633525</value>
<value node_number="118">-0.30959225,0.24977812500000002,0.24773575</value>
<value node_number="119">-0.256122125,0.1865325,0.27091475</value>
<value node_number="120">-0.307748625,0.265456875,0.160649125</value>
<value node_number="121">-0.36975975,0.297574,0.293075625</value>
<value node_number="122">-0.30433224999999997,0.234272125,0.3152065</value>
<value node_number="123">-0.251106875,0.258822875,0.130473125</value>
<value node_number="124">-0.30280475,0.287655625,0.239191875</value>
<value node_number="125">-0.2517095,0.227667,0.254290625</value>
</field>