<?xml version="1.0" encoding="utf-8" ?>
<field name="control_found_by_optimizer" type="control_field" dimensions="3" number_of_elements="512">
    <value cell_id="1">0.899553,-1.306743,1.407267</value>
    <value cell_id="2">2.661007,-3.491542,2.834198</value>
    <value cell_id="3">0.363032,-0.657993,0.548223</value>
    <value cell_id="4">1.043954,-1.708171,1.108735</value>
    <value cell_id="5">0.496037,-0.491989,0.522355</value>
    <value cell_id="6">1.394057,-1.288504,1.035829</value>
    <value cell_id="7">0.198833,-0.251110,0.207132</value>
    <value cell_id="8">0.547832,-0.644800,0.412982</value>
    <value cell_id="9">4.936181,-5.737779,3.209592</value>
    <value cell_id="10">6.949976,-6.997807,2.308134</value>
    <value cell_id="11">1.893018,-2.759683,1.275251</value>
    <value cell_id="12">2.383983,-3.279380,0.933270</value>
    <value cell_id="13">2.498390,-2.104652,1.175998</value>
    <value cell_id="14">3.397531,-2.587728,0.854434</value>
    <value cell_id="15">0.949683,-1.031867,0.475322</value>
    <value cell_id="16">1.212099,-1.248542,0.360213</value>
    <value cell_id="17">7.271433,-6.840669,0.541273</value>
    <value cell_id="18">5.906734,-5.219813,-0.975700</value>
    <value cell_id="19">2.472339,-3.177450,0.283581</value>
    <value cell_id="20">2.093110,-2.478843,-0.288501</value>
    <value cell_id="21">3.564679,-2.553109,0.250907</value>
    <value cell_id="22">2.877963,-1.985831,-0.287067</value>
    <value cell_id="23">1.283506,-1.209073,0.140135</value>
    <value cell_id="24">1.063076,-0.961889,-0.082334</value>
    <value cell_id="25">3.594602,-2.928927,-1.374551</value>
    <value cell_id="26">1.376077,-1.023863,-0.813385</value>
    <value cell_id="27">1.348260,-1.452650,-0.456800</value>
    <value cell_id="28">0.551954,-0.540445,-0.268715</value>
    <value cell_id="29">1.725297,-1.143597,-0.485707</value>
    <value cell_id="30">0.663803,-0.411781,-0.286512</value>
    <value cell_id="31">0.658611,-0.565622,-0.168908</value>
    <value cell_id="32">0.261672,-0.210729,-0.101969</value>
    <value cell_id="33">1.680913,-0.811430,2.765932</value>
    <value cell_id="34">5.474333,-2.406317,5.640872</value>
    <value cell_id="35">1.403104,-1.436213,2.252321</value>
    <value cell_id="36">4.351854,-3.990698,4.548366</value>
    <value cell_id="37">0.921352,-0.316477,1.034320</value>
    <value cell_id="38">2.769613,-0.854615,2.003865</value>
    <value cell_id="39">0.767851,-0.530800,0.831159</value>
    <value cell_id="40">2.256817,-1.427149,1.648722</value>
    <value cell_id="41">10.728681,-4.401475,6.232365</value>
    <value cell_id="42">15.202196,-5.549458,3.531875</value>
    <value cell_id="43">8.492100,-6.818299,5.130546</value>
    <value cell_id="44">12.370431,-8.346473,3.518096</value>
    <value cell_id="45">5.160397,-1.431679,2.173631</value>
    <value cell_id="46">7.017111,-1.732108,1.091707</value>
    <value cell_id="47">4.172417,-2.404385,1.876588</value>
    <value cell_id="48">5.766314,-2.915021,1.211878</value>
    <value cell_id="49">15.834661,-5.388035,-0.150550</value>
    <value cell_id="50">12.767289,-3.560628,-2.951890</value>
    <value cell_id="51">13.255678,-8.305618,0.542665</value>
    <value cell_id="52">10.220479,-6.081596,-1.863254</value>
    <value cell_id="53">7.172289,-1.925959,-0.115189</value>
    <value cell_id="54">5.814048,-1.468656,-1.011460</value>
    <value cell_id="55">6.027204,-2.947060,0.196956</value>
    <value cell_id="56">4.759644,-2.278973,-0.601881</value>
    <value cell_id="57">7.376182,-1.813332,-3.541422</value>
    <value cell_id="58">2.658005,-0.556485,-1.969771</value>
    <value cell_id="59">5.923781,-3.193701,-2.492013</value>
    <value cell_id="60">2.183545,-1.033060,-1.475625</value>
    <value cell_id="61">3.538928,-0.812369,-1.128214</value>
    <value cell_id="62">1.340874,-0.265151,-0.632837</value>
    <value cell_id="63">2.846067,-1.300687,-0.827011</value>
    <value cell_id="64">1.079786,-0.443100,-0.486117</value>
    <value cell_id="65">1.362903,0.737396,2.002738</value>
    <value cell_id="66">4.195528,2.061493,3.827940</value>
    <value cell_id="67">1.695812,0.104177,2.645193</value>
    <value cell_id="68">5.451689,0.173156,5.214591</value>
    <value cell_id="69">0.746596,0.289521,0.700577</value>
    <value cell_id="70">2.170268,0.809615,1.293811</value>
    <value cell_id="71">0.917952,0.014165,0.943282</value>
    <value cell_id="72">2.716190,0.063431,1.792131</value>
    <value cell_id="73">7.951523,3.756208,3.687501</value>
    <value cell_id="74">10.793470,4.530815,1.197392</value>
    <value cell_id="75">10.567729,0.436450,5.234575</value>
    <value cell_id="76">14.850573,0.253139,1.996821</value>
    <value cell_id="77">3.944261,1.358337,1.313124</value>
    <value cell_id="78">5.286322,1.560601,0.528179</value>
    <value cell_id="79">5.108114,0.230073,1.902097</value>
    <value cell_id="80">6.969684,0.116501,0.816430</value>
    <value cell_id="81">11.185366,3.970774,-1.822868</value>
    <value cell_id="82">9.020765,3.072797,-3.792378</value>
    <value cell_id="83">15.169528,-0.218442,-1.757538</value>
    <value cell_id="84">12.231218,0.217221,-3.985727</value>
    <value cell_id="85">5.497685,1.309199,-0.477379</value>
    <value cell_id="86">4.375493,0.918038,-1.187644</value>
    <value cell_id="87">7.110540,-0.201392,-0.558333</value>
    <value cell_id="88">5.683318,-0.193033,-1.264413</value>
    <value cell_id="89">5.441419,1.692713,-3.599830</value>
    <value cell_id="90">2.024483,0.559287,-1.805139</value>
    <value cell_id="91">7.252832,0.300293,-3.981998</value>
    <value cell_id="92">2.629592,0.108808,-2.083877</value>
    <value cell_id="93">2.690780,0.550854,-1.208098</value>
    <value cell_id="94">1.036824,0.206271,-0.627497</value>
    <value cell_id="95">3.475924,-0.038261,-1.276538</value>
    <value cell_id="96">1.334108,-0.004005,-0.679947</value>
    <value cell_id="97">0.318845,0.451365,0.427340</value>
    <value cell_id="98">0.843250,1.236956,0.752792</value>
    <value cell_id="99">0.822055,0.826686,1.145334</value>
    <value cell_id="100">2.353105,2.312151,2.099186</value>
    <value cell_id="101">0.184504,0.190192,0.163451</value>
    <value cell_id="102">0.499251,0.515348,0.316975</value>
    <value cell_id="103">0.460719,0.335884,0.409814</value>
    <value cell_id="104">1.269804,0.907279,0.746366</value>
    <value cell_id="105">1.366553,2.087050,0.642840</value>
    <value cell_id="106">1.725382,2.608691,0.133890</value>
    <value cell_id="107">4.166860,4.017862,1.942258</value>
    <value cell_id="108">5.463461,4.971369,0.548878</value>
    <value cell_id="109">0.765554,0.811325,0.243263</value>
    <value cell_id="110">0.987386,0.986088,0.047302</value>
    <value cell_id="111">2.180323,1.506622,0.704102</value>
    <value cell_id="112">2.894791,1.878688,0.219689</value>
    <value cell_id="113">1.903628,2.501588,-0.590480</value>
    <value cell_id="114">1.578289,1.788042,-1.032744</value>
    <value cell_id="115">5.919635,4.704914,-1.328497</value>
    <value cell_id="116">4.801283,3.339410,-2.574340</value>
    <value cell_id="117">1.062097,0.925664,-0.201171</value>
    <value cell_id="118">0.893547,0.673909,-0.375532</value>
    <value cell_id="119">3.078699,1.695878,-0.388888</value>
    <value cell_id="120">2.522497,1.212130,-0.843279</value>
    <value cell_id="121">0.997918,0.942064,-0.939025</value>
    <value cell_id="122">0.398903,0.315465,-0.464428</value>
    <value cell_id="123">2.979307,1.773997,-2.385136</value>
    <value cell_id="124">1.145979,0.591665,-1.170694</value>
    <value cell_id="125">0.567153,0.369039,-0.358549</value>
    <value cell_id="126">0.223904,0.127540,-0.182175</value>
    <value cell_id="127">1.564290,0.673727,-0.844686</value>
    <value cell_id="128">0.608448,0.235940,-0.433609</value>
    <value cell_id="129">0.063624,-2.971805,2.824326</value>
    <value cell_id="130">0.735643,-7.902881,6.023191</value>
    <value cell_id="131">0.063113,-1.410486,1.094656</value>
    <value cell_id="132">0.351371,-3.613626,2.340891</value>
    <value cell_id="133">0.789891,-2.231727,2.356086</value>
    <value cell_id="134">2.580178,-6.005177,4.873862</value>
    <value cell_id="135">0.331098,-1.096524,0.899414</value>
    <value cell_id="136">1.014500,-2.836580,1.867283</value>
    <value cell_id="137">2.368351,-12.992303,6.887277</value>
    <value cell_id="138">4.191735,-15.291887,4.162033</value>
    <value cell_id="139">0.860436,-5.875831,2.541486</value>
    <value cell_id="140">1.421606,-7.243943,1.515621</value>
    <value cell_id="141">5.176671,-9.980646,5.584234</value>
    <value cell_id="142">7.440689,-11.744890,3.888720</value>
    <value cell_id="143">1.856371,-4.592616,2.118187</value>
    <value cell_id="144">2.415652,-5.504021,1.451851</value>
    <value cell_id="145">4.730275,-14.528935,-0.029406</value>
    <value cell_id="146">4.487069,-10.857650,-2.888024</value>
    <value cell_id="147">1.487135,-6.897965,0.206440</value>
    <value cell_id="148">1.588431,-5.251029,-0.861907</value>
    <value cell_id="149">7.955171,-11.342742,0.535278</value>
    <value cell_id="150">6.677860,-8.529873,-1.934114</value>
    <value cell_id="151">2.564712,-5.320542,0.306961</value>
    <value cell_id="152">2.315042,-4.085957,-0.588164</value>
    <value cell_id="153">2.899644,-5.812452,-3.511894</value>
    <value cell_id="154">1.127425,-1.870370,-1.970178</value>
    <value cell_id="155">1.137743,-2.954084,-1.176092</value>
    <value cell_id="156">0.486780,-1.011925,-0.667289</value>
    <value cell_id="157">4.215817,-4.774066,-2.541518</value>
    <value cell_id="158">1.604109,-1.622177,-1.471614</value>
    <value cell_id="159">1.579183,-2.382775,-0.833787</value>
    <value cell_id="160">0.644557,-0.873313,-0.492670</value>
    <value cell_id="161">0.015099,-2.090468,5.821992</value>
    <value cell_id="162">1.184858,-6.271047,12.104316</value>
    <value cell_id="163">-0.005318,-3.439542,4.685819</value>
    <value cell_id="164">0.986567,-9.735002,9.989476</value>
    <value cell_id="165">1.402656,-1.391075,4.645336</value>
    <value cell_id="166">5.081918,-4.382704,9.760441</value>
    <value cell_id="167">1.175269,-2.494116,3.804803</value>
    <value cell_id="168">4.044477,-7.043837,7.882490</value>
    <value cell_id="169">4.571422,-11.529026,13.158431</value>
    <value cell_id="170">10.511333,-13.857033,5.527565</value>
    <value cell_id="171">3.875078,-16.218387,11.068205</value>
    <value cell_id="172">7.888554,-17.916535,6.112484</value>
    <value cell_id="173">11.524013,-8.430161,10.859362</value>
    <value cell_id="174">18.931646,-10.776052,5.968694</value>
    <value cell_id="175">8.775809,-12.257483,8.938219</value>
    <value cell_id="176">14.333858,-14.791234,5.990109</value>
    <value cell_id="177">13.816146,-10.030998,-3.537716</value>
    <value cell_id="178">8.374479,-6.285491,-9.752120</value>
    <value cell_id="179">9.064506,-16.879387,-1.564664</value>
    <value cell_id="180">7.969885,-11.824341,-6.128861</value>
    <value cell_id="181">19.773012,-9.731752,-0.521162</value>
    <value cell_id="182">15.220796,-5.481876,-5.625125</value>
    <value cell_id="183">15.524742,-14.176902,0.778195</value>
    <value cell_id="184">11.959253,-9.939974,-3.786696</value>
    <value cell_id="185">4.403768,-3.186243,-9.871724</value>
    <value cell_id="186">1.692600,-1.182838,-5.044616</value>
    <value cell_id="187">4.525584,-5.667177,-6.955194</value>
    <value cell_id="188">1.602489,-1.837881,-3.726383</value>
    <value cell_id="189">8.032026,-2.509050,-7.048632</value>
    <value cell_id="190">2.813276,-0.818047,-3.718380</value>
    <value cell_id="191">6.753330,-4.992100,-4.913300</value>
    <value cell_id="192">2.452697,-1.574476,-2.754092</value>
    <value cell_id="193">0.159578,1.258674,4.547962</value>
    <value cell_id="194">0.860728,3.709198,9.031731</value>
    <value cell_id="195">0.029391,0.013470,5.809342</value>
    <value cell_id="196">1.040929,0.173096,11.928413</value>
    <value cell_id="197">1.158588,1.144833,3.477367</value>
    <value cell_id="198">3.977010,3.348913,6.857898</value>
    <value cell_id="199">1.460070,0.194014,4.598829</value>
    <value cell_id="200">5.182933,0.392502,9.245699</value>
    <value cell_id="201">3.145672,6.590189,8.870323</value>
    <value cell_id="202">4.624728,8.631066,2.436398</value>
    <value cell_id="203">4.777851,-1.019376,12.152781</value>
    <value cell_id="204">7.661248,-1.547758,4.059570</value>
    <value cell_id="205">8.356628,6.227748,6.671326</value>
    <value cell_id="206">11.488651,7.786457,1.730353</value>
    <value cell_id="207">10.677102,0.445703,9.474665</value>
    <value cell_id="208">16.973579,0.521094,3.676453</value>
    <value cell_id="209">3.796626,9.921467,-6.717696</value>
    <value cell_id="210">3.069094,6.906783,-11.282937</value>
    <value cell_id="211">9.870416,0.775350,-6.305757</value>
    <value cell_id="212">6.709633,1.498218,-12.512096</value>
    <value cell_id="213">11.412917,7.421233,-4.367436</value>
    <value cell_id="214">9.603274,5.602204,-7.697841</value>
    <value cell_id="215">17.018554,0.106361,-3.430217</value>
    <value cell_id="216">14.565946,1.686411,-8.318738</value>
    <value cell_id="217">1.927549,3.150090,-9.112860</value>
    <value cell_id="218">0.752417,0.882438,-4.184321</value>
    <value cell_id="219">3.680190,0.478960,-10.939210</value>
    <value cell_id="220">1.406052,-0.034782,-5.216716</value>
    <value cell_id="221">5.692727,2.813385,-6.809161</value>
    <value cell_id="222">2.041026,0.879272,-3.242710</value>
    <value cell_id="223">8.190843,0.904496,-7.992965</value>
    <value cell_id="224">2.802061,0.242958,-3.940253</value>
    <value cell_id="225">0.058825,0.810826,0.977820</value>
    <value cell_id="226">0.140599,2.234136,1.890320</value>
    <value cell_id="227">0.125320,1.496991,2.646195</value>
    <value cell_id="228">0.503889,4.129383,5.324813</value>
    <value cell_id="229">0.282053,0.686109,0.730579</value>
    <value cell_id="230">0.758755,1.892221,1.354460</value>
    <value cell_id="231">0.700662,1.288044,1.998924</value>
    <value cell_id="232">2.187226,3.645345,3.849197</value>
    <value cell_id="233">0.070568,3.985439,1.771615</value>
    <value cell_id="234">-0.140996,5.357163,0.453014</value>
    <value cell_id="235">0.976434,7.554171,5.210324</value>
    <value cell_id="236">1.211349,10.385645,1.288971</value>
    <value cell_id="237">1.187286,3.306170,1.222264</value>
    <value cell_id="238">1.339306,4.398083,0.261656</value>
    <value cell_id="239">4.119445,6.431892,3.678328</value>
    <value cell_id="240">5.192619,8.393905,0.951206</value>
    <value cell_id="241">-0.093579,5.200855,-1.073147</value>
    <value cell_id="242">-0.055873,3.871208,-1.946023</value>
    <value cell_id="243">0.954072,10.568591,-3.530670</value>
    <value cell_id="244">0.778309,7.530464,-6.000759</value>
    <value cell_id="245">1.498037,4.278386,-1.016677</value>
    <value cell_id="246">1.249565,3.047766,-1.685656</value>
    <value cell_id="247">5.377072,8.105256,-2.785570</value>
    <value cell_id="248">4.398481,5.751051,-4.685719</value>
    <value cell_id="249">0.019964,2.035935,-1.829621</value>
    <value cell_id="250">0.037894,0.642998,-0.946796</value>
    <value cell_id="251">0.575762,3.729567,-5.251420</value>
    <value cell_id="252">0.289326,1.107243,-2.547248</value>
    <value cell_id="253">0.798346,1.549766,-1.489200</value>
    <value cell_id="254">0.337418,0.505893,-0.744191</value>
    <value cell_id="255">2.760909,2.954726,-4.105425</value>
    <value cell_id="256">1.075361,0.941805,-1.972052</value>
    <value cell_id="257">-1.219289,-2.432509,1.808772</value>
    <value cell_id="258">-3.087118,-6.360135,3.513299</value>
    <value cell_id="259">-0.469859,-1.172261,0.632963</value>
    <value cell_id="260">-1.068302,-2.974253,1.246198</value>
    <value cell_id="261">-0.762553,-3.056782,2.556539</value>
    <value cell_id="262">-1.854819,-8.102278,5.320837</value>
    <value cell_id="263">-0.275015,-1.451611,0.963424</value>
    <value cell_id="264">-0.565779,-3.693211,1.992605</value>
    <value cell_id="265">-4.592501,-10.113718,3.680033</value>
    <value cell_id="266">-4.521581,-12.367626,1.372981</value>
    <value cell_id="267">-1.477431,-4.711592,1.269475</value>
    <value cell_id="268">-1.347334,-5.619288,0.603558</value>
    <value cell_id="269">-2.286258,-13.102081,5.893268</value>
    <value cell_id="270">-0.912740,-15.736868,3.184067</value>
    <value cell_id="271">-0.573643,-5.915658,2.122441</value>
    <value cell_id="272">-0.124156,-7.247527,1.201311</value>
    <value cell_id="273">-3.743412,-11.330991,-1.671246</value>
    <value cell_id="274">-2.554529,-8.335444,-3.719651</value>
    <value cell_id="275">-1.061245,-5.374830,-0.327335</value>
    <value cell_id="276">-0.688937,-4.013907,-1.162759</value>
    <value cell_id="277">0.191767,-14.524580,-0.827772</value>
    <value cell_id="278">0.701448,-10.578702,-3.486788</value>
    <value cell_id="279">0.298115,-6.879664,0.011077</value>
    <value cell_id="280">0.407777,-5.109957,-1.092352</value>
    <value cell_id="281">-1.364126,-4.271545,-3.502033</value>
    <value cell_id="282">-0.464523,-1.414670,-1.798277</value>
    <value cell_id="283">-0.331449,-2.170057,-1.203567</value>
    <value cell_id="284">-0.091384,-0.734079,-0.633133</value>
    <value cell_id="285">0.532604,-5.449718,-3.906989</value>
    <value cell_id="286">0.307002,-1.776395,-2.119089</value>
    <value cell_id="287">0.382511,-2.792043,-1.334817</value>
    <value cell_id="288">0.195342,-0.945041,-0.729571</value>
    <value cell_id="289">-2.444171,-1.781462,4.067708</value>
    <value cell_id="290">-6.778398,-4.921241,8.285960</value>
    <value cell_id="291">-1.937614,-2.748287,3.092201</value>
    <value cell_id="292">-5.135608,-7.740501,6.234658</value>
    <value cell_id="293">-1.549321,-2.195797,5.315257</value>
    <value cell_id="294">-3.636103,-6.470392,11.007060</value>
    <value cell_id="295">-1.223302,-3.460344,4.228693</value>
    <value cell_id="296">-3.022415,-9.977248,8.682477</value>
    <value cell_id="297">-11.638301,-8.867806,9.125161</value>
    <value cell_id="298">-14.667629,-10.237716,3.184362</value>
    <value cell_id="299">-8.411406,-12.740977,6.671739</value>
    <value cell_id="300">-9.574151,-15.460083,2.226345</value>
    <value cell_id="301">-4.944854,-12.377076,11.750364</value>
    <value cell_id="302">-5.883079,-14.939018,4.774138</value>
    <value cell_id="303">-4.507723,-17.397823,9.914239</value>
    <value cell_id="304">-2.898716,-19.861157,4.817781</value>
    <value cell_id="305">-13.753313,-8.948509,-5.134410</value>
    <value cell_id="306">-10.537789,-5.793334,-9.881444</value>
    <value cell_id="307">-7.780826,-13.248997,-3.939227</value>
    <value cell_id="308">-5.709214,-9.060464,-7.071603</value>
    <value cell_id="309">-2.302933,-12.019813,-6.902055</value>
    <value cell_id="310">-2.307575,-7.452420,-11.639538</value>
    <value cell_id="311">-0.838800,-17.237491,-3.826657</value>
    <value cell_id="312">-0.115539,-11.604609,-7.134026</value>
    <value cell_id="313">-5.887275,-3.109102,-8.897328</value>
    <value cell_id="314">-1.897938,-1.092368,-4.230495</value>
    <value cell_id="315">-3.435807,-4.682556,-6.533808</value>
    <value cell_id="316">-1.214387,-1.552784,-3.208583</value>
    <value cell_id="317">-1.592083,-3.724950,-10.656086</value>
    <value cell_id="318">-0.463511,-1.232074,-5.147144</value>
    <value cell_id="319">-0.193725,-5.665066,-7.511606</value>
    <value cell_id="320">-0.032047,-1.798064,-3.878853</value>
    <value cell_id="321">-1.857581,0.725215,3.696331</value>
    <value cell_id="322">-5.180194,2.315311,7.492839</value>
    <value cell_id="323">-2.383129,-0.413070,4.411816</value>
    <value cell_id="324">-6.708010,-0.735073,9.181631</value>
    <value cell_id="325">-1.152186,0.953937,4.629354</value>
    <value cell_id="326">-3.048929,2.909118,9.404812</value>
    <value cell_id="327">-1.525067,-0.383294,5.601722</value>
    <value cell_id="328">-3.883964,-1.347740,11.895861</value>
    <value cell_id="329">-8.919687,5.049204,7.875637</value>
    <value cell_id="330">-11.650072,7.664349,4.115705</value>
    <value cell_id="331">-11.646892,-0.686787,9.532414</value>
    <value cell_id="332">-15.537270,-0.376585,3.347579</value>
    <value cell_id="333">-4.434720,5.595768,10.001398</value>
    <value cell_id="334">-5.650855,8.386676,3.486808</value>
    <value cell_id="335">-6.138384,-2.504443,12.881247</value>
    <value cell_id="336">-6.857116,-1.440508,5.049004</value>
    <value cell_id="337">-13.089144,7.222496,-2.290508</value>
    <value cell_id="338">-10.742011,4.429577,-7.017135</value>
    <value cell_id="339">-18.322759,0.006064,-4.389037</value>
    <value cell_id="340">-12.896521,-0.503181,-9.814697</value>
    <value cell_id="341">-6.790211,9.333538,-4.558921</value>
    <value cell_id="342">-6.307475,6.175008,-10.402076</value>
    <value cell_id="343">-6.571258,0.642458,-7.479087</value>
    <value cell_id="344">-5.021488,-0.462966,-13.837689</value>
    <value cell_id="345">-6.171618,2.046425,-6.964372</value>
    <value cell_id="346">-2.129460,0.559990,-3.475026</value>
    <value cell_id="347">-6.860768,-0.457584,-8.809592</value>
    <value cell_id="348">-2.257803,-0.261466,-4.329016</value>
    <value cell_id="349">-3.250784,2.773315,-9.171420</value>
    <value cell_id="350">-1.007032,0.787045,-4.314489</value>
    <value cell_id="351">-2.835317,-0.256431,-11.415252</value>
    <value cell_id="352">-0.812681,-0.232310,-5.356360</value>
    <value cell_id="353">-0.451823,0.611582,0.838374</value>
    <value cell_id="354">-1.221247,1.730383,1.675550</value>
    <value cell_id="355">-1.150788,1.042349,2.244031</value>
    <value cell_id="356">-3.214819,3.030557,4.514287</value>
    <value cell_id="357">-0.258967,0.778710,1.020720</value>
    <value cell_id="358">-0.711507,2.238659,1.994526</value>
    <value cell_id="359">-0.683754,1.340414,2.754738</value>
    <value cell_id="360">-1.882476,3.967716,5.552089</value>
    <value cell_id="361">-2.051095,3.061626,1.874405</value>
    <value cell_id="362">-2.622613,3.983268,1.175152</value>
    <value cell_id="363">-5.453640,5.674764,4.872482</value>
    <value cell_id="364">-6.923507,7.923278,3.056980</value>
    <value cell_id="365">-1.249946,4.014814,1.977722</value>
    <value cell_id="366">-1.746490,5.195989,0.881107</value>
    <value cell_id="367">-3.203017,7.230925,5.854719</value>
    <value cell_id="368">-4.115426,10.036824,2.295164</value>
    <value cell_id="369">-2.746193,3.903643,-0.107338</value>
    <value cell_id="370">-2.336273,2.865299,-1.201781</value>
    <value cell_id="371">-7.489944,7.587152,-0.697944</value>
    <value cell_id="372">-6.283721,5.297551,-3.715056</value>
    <value cell_id="373">-2.039164,5.058931,-0.638118</value>
    <value cell_id="374">-1.581930,3.794045,-1.710018</value>
    <value cell_id="375">-4.899472,10.062088,-2.243539</value>
    <value cell_id="376">-3.860692,7.191717,-5.206324</value>
    <value cell_id="377">-1.470807,1.527502,-1.429252</value>
    <value cell_id="378">-0.574498,0.511442,-0.783167</value>
    <value cell_id="379">-3.924814,2.640646,-4.107295</value>
    <value cell_id="380">-1.441869,0.845581,-2.094361</value>
    <value cell_id="381">-0.930328,2.006164,-1.804871</value>
    <value cell_id="382">-0.345949,0.639543,-0.983992</value>
    <value cell_id="383">-2.266966,3.552565,-5.165951</value>
    <value cell_id="384">-0.772901,1.081746,-2.641321</value>
    <value cell_id="385">-0.517804,-0.516740,0.370897</value>
    <value cell_id="386">-1.329224,-1.309239,0.632311</value>
    <value cell_id="387">-0.205957,-0.262467,0.130126</value>
    <value cell_id="388">-0.507017,-0.659693,0.214010</value>
    <value cell_id="389">-1.078006,-1.402343,1.029351</value>
    <value cell_id="390">-2.719605,-3.648850,1.905181</value>
    <value cell_id="391">-0.421866,-0.699981,0.356945</value>
    <value cell_id="392">-1.008227,-1.770132,0.640263</value>
    <value cell_id="393">-2.179368,-2.084661,0.435207</value>
    <value cell_id="394">-2.674706,-2.524777,-0.098552</value>
    <value cell_id="395">-0.786703,-1.032010,0.144348</value>
    <value cell_id="396">-0.906512,-1.238707,-0.056402</value>
    <value cell_id="397">-4.320006,-5.831580,1.553414</value>
    <value cell_id="398">-5.059521,-7.034027,0.212408</value>
    <value cell_id="399">-1.499351,-2.780623,0.540356</value>
    <value cell_id="400">-1.619044,-3.334274,0.081339</value>
    <value cell_id="401">-2.513452,-2.439830,-0.710004</value>
    <value cell_id="402">-1.801492,-1.887991,-1.049992</value>
    <value cell_id="403">-0.847560,-1.194779,-0.292148</value>
    <value cell_id="404">-0.603583,-0.892679,-0.390420</value>
    <value cell_id="405">-4.612274,-6.655472,-1.405257</value>
    <value cell_id="406">-3.269558,-4.922602,-2.645381</value>
    <value cell_id="407">-1.451407,-3.200375,-0.482840</value>
    <value cell_id="408">-1.029215,-2.388620,-0.884601</value>
    <value cell_id="409">-1.033035,-1.061875,-0.957094</value>
    <value cell_id="410">-0.386919,-0.367524,-0.465240</value>
    <value cell_id="411">-0.353323,-0.525089,-0.345887</value>
    <value cell_id="412">-0.128422,-0.190343,-0.175547</value>
    <value cell_id="413">-1.785782,-2.703825,-2.381484</value>
    <value cell_id="414">-0.660016,-0.907919,-1.161092</value>
    <value cell_id="415">-0.559599,-1.343032,-0.826427</value>
    <value cell_id="416">-0.196830,-0.465803,-0.421213</value>
    <value cell_id="417">-1.025609,-0.385888,0.838483</value>
    <value cell_id="418">-2.852077,-0.912302,1.545364</value>
    <value cell_id="419">-0.822985,-0.577029,0.647855</value>
    <value cell_id="420">-2.217592,-1.437592,1.146239</value>
    <value cell_id="421">-2.108446,-1.057271,2.346028</value>
    <value cell_id="422">-5.883673,-2.696719,4.534025</value>
    <value cell_id="423">-1.680285,-1.596979,1.802059</value>
    <value cell_id="424">-4.531679,-4.163756,3.452156</value>
    <value cell_id="425">-5.010845,-1.376277,1.402523</value>
    <value cell_id="426">-6.428261,-1.734869,0.310217</value>
    <value cell_id="427">-3.779427,-2.310879,0.868122</value>
    <value cell_id="428">-4.799201,-2.877202,-0.044177</value>
    <value cell_id="429">-10.299498,-4.508599,4.533016</value>
    <value cell_id="430">-13.214380,-5.295163,1.181535</value>
    <value cell_id="431">-7.614256,-6.903198,3.068939</value>
    <value cell_id="432">-9.590661,-8.404749,0.398346</value>
    <value cell_id="433">-6.431297,-1.842418,-1.266314</value>
    <value cell_id="434">-4.979243,-1.331555,-2.093491</value>
    <value cell_id="435">-4.657702,-2.787332,-1.132042</value>
    <value cell_id="436">-3.538052,-2.079224,-1.868120</value>
    <value cell_id="437">-13.173443,-5.223663,-3.369444</value>
    <value cell_id="438">-10.149166,-3.581296,-5.685743</value>
    <value cell_id="439">-8.902778,-7.631965,-2.583514</value>
    <value cell_id="440">-6.515266,-5.556500,-4.696129</value>
    <value cell_id="441">-2.832660,-0.693034,-1.890958</value>
    <value cell_id="442">-1.022393,-0.245564,-0.936362</value>
    <value cell_id="443">-1.998696,-1.145100,-1.590065</value>
    <value cell_id="444">-0.741756,-0.380763,-0.745995</value>
    <value cell_id="445">-5.727506,-1.945613,-5.268449</value>
    <value cell_id="446">-2.017080,-0.699577,-2.556043</value>
    <value cell_id="447">-3.736704,-2.937512,-4.146957</value>
    <value cell_id="448">-1.380918,-0.983438,-1.988825</value>
    <value cell_id="449">-0.838910,0.225777,0.738876</value>
    <value cell_id="450">-2.345203,0.698861,1.448394</value>
    <value cell_id="451">-1.028504,-0.040709,0.878911</value>
    <value cell_id="452">-2.906776,0.011621,1.633490</value>
    <value cell_id="453">-1.681518,0.506480,2.117218</value>
    <value cell_id="454">-4.735273,1.673147,4.083879</value>
    <value cell_id="455">-2.077729,-0.166713,2.542981</value>
    <value cell_id="456">-5.885658,-0.209445,4.858161</value>
    <value cell_id="457">-4.132035,1.245525,1.681659</value>
    <value cell_id="458">-5.442585,1.331329,0.961562</value>
    <value cell_id="459">-5.150680,0.174692,1.650894</value>
    <value cell_id="460">-6.670644,0.048899,0.708666</value>
    <value cell_id="461">-8.285660,3.205912,4.289207</value>
    <value cell_id="462">-11.043548,4.043386,2.505751</value>
    <value cell_id="463">-10.526360,0.084285,4.768741</value>
    <value cell_id="464">-14.192119,-0.032638,1.992041</value>
    <value cell_id="465">-5.510958,1.176439,-0.094724</value>
    <value cell_id="466">-4.383322,0.900424,-1.066893</value>
    <value cell_id="467">-6.713916,-0.065875,-0.781390</value>
    <value cell_id="468">-5.328251,-0.002188,-1.750315</value>
    <value cell_id="469">-11.905582,3.853954,-0.557380</value>
    <value cell_id="470">-9.345360,2.703894,-3.388856</value>
    <value cell_id="471">-14.838886,0.007107,-2.100728</value>
    <value cell_id="472">-11.450202,-0.024408,-5.077977</value>
    <value cell_id="473">-2.632180,0.477381,-1.289817</value>
    <value cell_id="474">-0.993612,0.138471,-0.721302</value>
    <value cell_id="475">-3.134822,0.010991,-1.768901</value>
    <value cell_id="476">-1.157129,-0.032542,-0.924973</value>
    <value cell_id="477">-5.426558,1.199196,-3.752313</value>
    <value cell_id="478">-1.984600,0.320364,-2.008130</value>
    <value cell_id="479">-6.417360,-0.101904,-4.981360</value>
    <value cell_id="480">-2.297970,-0.166612,-2.548948</value>
    <value cell_id="481">-0.210708,0.159075,0.199676</value>
    <value cell_id="482">-0.559587,0.416787,0.414377</value>
    <value cell_id="483">-0.526333,0.287344,0.484437</value>
    <value cell_id="484">-1.444396,0.785783,0.982775</value>
    <value cell_id="485">-0.417328,0.389851,0.519425</value>
    <value cell_id="486">-1.115140,1.065670,1.061014</value>
    <value cell_id="487">-1.047337,0.695711,1.332394</value>
    <value cell_id="488">-2.883550,1.975505,2.656044</value>
    <value cell_id="489">-0.929548,0.675233,0.501570</value>
    <value cell_id="490">-1.160209,0.811659,0.397447</value>
    <value cell_id="491">-2.512182,1.291584,1.172132</value>
    <value cell_id="492">-3.186716,1.494041,0.863846</value>
    <value cell_id="493">-1.847689,1.825683,1.238296</value>
    <value cell_id="494">-2.310060,2.305534,0.926223</value>
    <value cell_id="495">-4.973626,3.451207,2.994736</value>
    <value cell_id="496">-6.362241,4.377256,2.075331</value>
    <value cell_id="497">-1.193040,0.762486,0.105045</value>
    <value cell_id="498">-0.992446,0.561066,-0.182983</value>
    <value cell_id="499">-3.274384,1.379912,0.146581</value>
    <value cell_id="500">-2.656002,1.023169,-0.537304</value>
    <value cell_id="501">-2.398432,2.196008,0.117130</value>
    <value cell_id="502">-2.011314,1.596587,-0.623047</value>
    <value cell_id="503">-6.693037,4.075359,0.045824</value>
    <value cell_id="504">-5.505370,2.950913,-1.833754</value>
    <value cell_id="505">-0.640577,0.314583,-0.277639</value>
    <value cell_id="506">-0.259981,0.110782,-0.166902</value>
    <value cell_id="507">-1.657681,0.555761,-0.739739</value>
    <value cell_id="508">-0.646070,0.185895,-0.434221</value>
    <value cell_id="509">-1.296481,0.879850,-0.813250</value>
    <value cell_id="510">-0.523397,0.300781,-0.461053</value>
    <value cell_id="511">-3.414901,1.507772,-2.213046</value>
    <value cell_id="512">-1.309780,0.490556,-1.215204</value>
</field>
