<?xml version="1.0" encoding="utf-8" ?>
<field name="control_found_by_optimizer" type="control_field" dimensions="3" number_of_elements="216">
    <value cell_id="1">-0.099589,-1.504914,-1.005135</value>
    <value cell_id="2">-0.236561,-2.881557,-3.792523</value>
    <value cell_id="3">-0.326126,-2.664813,-7.610574</value>
    <value cell_id="4">-0.387471,-0.656331,-7.611059</value>
    <value cell_id="5">-0.267808,1.109698,-4.251812</value>
    <value cell_id="6">-0.107296,0.910264,-1.337525</value>
    <value cell_id="7">-0.199570,-4.581942,-1.645782</value>
    <value cell_id="8">-0.633185,-10.655920,-7.893927</value>
    <value cell_id="9">-1.147810,-10.292407,-19.100880</value>
    <value cell_id="10">-1.376104,1.978617,-21.320682</value>
    <value cell_id="11">-0.751669,7.175734,-9.724021</value>
    <value cell_id="12">-0.267599,3.681962,-2.225882</value>
    <value cell_id="13">-0.192265,-7.850330,-0.883940</value>
    <value cell_id="14">-0.965061,-21.239233,-6.150065</value>
    <value cell_id="15">-2.548555,-21.849671,-17.549458</value>
    <value cell_id="16">-2.405427,14.583836,-24.205681</value>
    <value cell_id="17">-1.207891,19.088412,-8.940445</value>
    <value cell_id="18">-0.385498,7.537858,-1.359196</value>
    <value cell_id="19">-0.162588,-7.219396,0.321935</value>
    <value cell_id="20">-0.521758,-17.764953,3.611372</value>
    <value cell_id="21">-1.275861,-14.491998,14.256394</value>
    <value cell_id="22">-1.784260,22.245385,14.668284</value>
    <value cell_id="23">-1.182166,21.796078,5.495738</value>
    <value cell_id="24">-0.434245,8.181565,0.579193</value>
    <value cell_id="25">-0.141358,-3.722894,1.529864</value>
    <value cell_id="26">-0.356386,-7.083480,7.676830</value>
    <value cell_id="27">-0.739953,-2.873070,18.543547</value>
    <value cell_id="28">-0.745939,9.710505,21.035199</value>
    <value cell_id="29">-0.554326,10.787771,9.101796</value>
    <value cell_id="30">-0.252756,4.767730,2.015937</value>
    <value cell_id="31">-0.059095,-0.957571,1.025205</value>
    <value cell_id="32">-0.140485,-1.258877,3.916989</value>
    <value cell_id="33">-0.203101,0.100284,7.911956</value>
    <value cell_id="34">-0.212830,2.194031,8.448623</value>
    <value cell_id="35">-0.175050,2.635828,4.415151</value>
    <value cell_id="36">-0.086521,1.450050,1.304081</value>
    <value cell_id="37">-0.164392,-2.170530,-1.504851</value>
    <value cell_id="38">-0.404110,-3.942981,-4.958588</value>
    <value cell_id="39">-0.587072,-3.364152,-8.831665</value>
    <value cell_id="40">-0.617543,-0.824606,-9.245604</value>
    <value cell_id="41">-0.430154,1.475517,-5.803496</value>
    <value cell_id="42">-0.177327,1.356913,-2.005143</value>
    <value cell_id="43">-0.354960,-6.020409,-2.279304</value>
    <value cell_id="44">-1.024496,-12.138934,-8.849551</value>
    <value cell_id="45">-1.710828,-10.613680,-18.371666</value>
    <value cell_id="46">-1.727442,1.446622,-20.674924</value>
    <value cell_id="47">-1.107348,7.620450,-11.399900</value>
    <value cell_id="48">-0.425713,4.829655,-3.327425</value>
    <value cell_id="49">-0.427443,-9.317327,-1.170697</value>
    <value cell_id="50">-1.461655,-20.729049,-5.475686</value>
    <value cell_id="51">-2.873222,-19.676684,-14.626355</value>
    <value cell_id="52">-2.718050,11.369622,-19.646884</value>
    <value cell_id="53">-1.695152,17.930569,-8.850715</value>
    <value cell_id="54">-0.615303,8.917303,-2.073202</value>
    <value cell_id="55">-0.352537,-8.647552,0.638678</value>
    <value cell_id="56">-1.091223,-17.870588,4.477668</value>
    <value cell_id="57">-2.238428,-13.569077,14.784563</value>
    <value cell_id="58">-2.450496,20.975573,15.911433</value>
    <value cell_id="59">-1.623991,20.957910,5.257099</value>
    <value cell_id="60">-0.616120,9.475755,0.775149</value>
    <value cell_id="61">-0.241841,-4.830452,2.105557</value>
    <value cell_id="62">-0.672120,-8.045553,8.515302</value>
    <value cell_id="63">-1.196181,-2.776201,17.937721</value>
    <value cell_id="64">-1.307145,10.418864,19.480073</value>
    <value cell_id="65">-0.942957,12.314296,10.146799</value>
    <value cell_id="66">-0.398560,6.157720,2.726120</value>
    <value cell_id="67">-0.103234,-1.423603,1.500898</value>
    <value cell_id="68">-0.256342,-1.741360,4.951374</value>
    <value cell_id="69">-0.387212,0.319066,8.798207</value>
    <value cell_id="70">-0.418223,2.988888,9.302577</value>
    <value cell_id="71">-0.325129,3.873203,5.698313</value>
    <value cell_id="72">-0.150617,2.194975,1.882135</value>
    <value cell_id="73">-0.163409,-1.656325,-1.159254</value>
    <value cell_id="74">-0.391462,-2.885246,-3.335086</value>
    <value cell_id="75">-0.560136,-2.340077,-5.472008</value>
    <value cell_id="76">-0.564498,-0.424225,-5.824074</value>
    <value cell_id="77">-0.402739,1.129394,-4.003836</value>
    <value cell_id="78">-0.172718,1.028329,-1.560076</value>
    <value cell_id="79">-0.360513,-4.102333,-1.700150</value>
    <value cell_id="80">-0.911216,-7.259299,-5.202530</value>
    <value cell_id="81">-1.357690,-5.489864,-9.116998</value>
    <value cell_id="82">-1.361137,0.663203,-10.218511</value>
    <value cell_id="83">-0.955027,4.430263,-6.796788</value>
    <value cell_id="84">-0.400697,3.191763,-2.511382</value>
    <value cell_id="85">-0.465466,-5.827579,-0.807717</value>
    <value cell_id="86">-1.232189,-10.299411,-2.505778</value>
    <value cell_id="87">-1.914710,-6.956968,-4.658739</value>
    <value cell_id="88">-1.941736,4.256463,-6.471963</value>
    <value cell_id="89">-1.352259,8.924471,-4.225534</value>
    <value cell_id="90">-0.558884,5.464423,-1.529601</value>
    <value cell_id="91">-0.418519,-5.405644,0.769561</value>
    <value cell_id="92">-1.113165,-8.835736,2.873671</value>
    <value cell_id="93">-1.784774,-3.792845,5.740086</value>
    <value cell_id="94">-1.863288,7.965748,5.956168</value>
    <value cell_id="95">-1.309085,10.700855,2.774964</value>
    <value cell_id="96">-0.546451,5.934813,0.667736</value>
    <value cell_id="97">-0.278826,-3.221339,1.702400</value>
    <value cell_id="98">-0.716360,-4.611247,5.302802</value>
    <value cell_id="99">-1.112866,-0.849937,9.209044</value>
    <value cell_id="100">-1.184458,5.744784,9.681174</value>
    <value cell_id="101">-0.866214,7.530394,5.978752</value>
    <value cell_id="102">-0.375336,4.220371,2.022036</value>
    <value cell_id="103">-0.115927,-1.074041,1.171001</value>
    <value cell_id="104">-0.283518,-1.275298,3.331149</value>
    <value cell_id="105">-0.421679,0.235148,5.374672</value>
    <value cell_id="106">-0.449631,2.277920,5.616642</value>
    <value cell_id="107">-0.340635,2.948872,3.772527</value>
    <value cell_id="108">-0.153868,1.712182,1.417865</value>
    <value cell_id="109">-0.114719,-0.747520,-0.519548</value>
    <value cell_id="110">-0.262752,-1.234302,-1.277875</value>
    <value cell_id="111">-0.364398,-0.931195,-1.900514</value>
    <value cell_id="112">-0.364899,-0.094389,-2.043168</value>
    <value cell_id="113">-0.267016,0.522597,-1.562113</value>
    <value cell_id="114">-0.118809,0.457959,-0.702696</value>
    <value cell_id="115">-0.253026,-1.614612,-0.723999</value>
    <value cell_id="116">-0.579613,-2.502874,-1.729648</value>
    <value cell_id="117">-0.802483,-1.597958,-2.508010</value>
    <value cell_id="118">-0.809747,0.255578,-2.780196</value>
    <value cell_id="119">-0.597383,1.542556,-2.270055</value>
    <value cell_id="120">-0.266711,1.216228,-1.068684</value>
    <value cell_id="121">-0.336346,-2.054021,-0.273481</value>
    <value cell_id="122">-0.772037,-2.871598,-0.572600</value>
    <value cell_id="123">-1.067430,-1.235760,-0.726310</value>
    <value cell_id="124">-1.091319,1.071587,-0.985728</value>
    <value cell_id="125">-0.809185,2.641906,-1.077294</value>
    <value cell_id="126">-0.362065,1.923863,-0.594173</value>
    <value cell_id="127">-0.322498,-1.862100,0.479207</value>
    <value cell_id="128">-0.754239,-2.358430,1.141272</value>
    <value cell_id="129">-1.059723,-0.397404,1.462301</value>
    <value cell_id="130">-1.079752,1.876453,1.364865</value>
    <value cell_id="131">-0.796252,3.232828,0.924006</value>
    <value cell_id="132">-0.355328,2.163418,0.346098</value>
    <value cell_id="133">-0.223513,-1.197273,0.846850</value>
    <value cell_id="134">-0.525904,-1.428377,2.017970</value>
    <value cell_id="135">-0.747968,0.050349,2.813603</value>
    <value cell_id="136">-0.769275,1.959505,2.835580</value>
    <value cell_id="137">-0.569814,2.760907,2.080365</value>
    <value cell_id="138">-0.254604,1.716272,0.891334</value>
    <value cell_id="139">-0.094873,-0.460382,0.559570</value>
    <value cell_id="140">-0.222691,-0.511224,1.344193</value>
    <value cell_id="141">-0.318388,0.153251,1.927409</value>
    <value cell_id="142">-0.329947,1.037652,1.975187</value>
    <value cell_id="143">-0.246431,1.336757,1.450521</value>
    <value cell_id="144">-0.110882,0.798427,0.629320</value>
    <value cell_id="145">-0.057796,-0.136080,-0.087128</value>
    <value cell_id="146">-0.126916,-0.192073,-0.126560</value>
    <value cell_id="147">-0.171013,-0.108358,-0.103747</value>
    <value cell_id="148">-0.171446,0.027240,-0.119884</value>
    <value cell_id="149">-0.128134,0.106810,-0.167091</value>
    <value cell_id="150">-0.058702,0.083721,-0.119637</value>
    <value cell_id="151">-0.127288,-0.192840,-0.095293</value>
    <value cell_id="152">-0.274344,-0.177109,-0.063433</value>
    <value cell_id="153">-0.363912,-0.001502,0.092515</value>
    <value cell_id="154">-0.366312,0.076721,0.096023</value>
    <value cell_id="155">-0.277175,0.154918,-0.106925</value>
    <value cell_id="156">-0.128477,0.143267,-0.148533</value>
    <value cell_id="157">-0.172437,-0.132507,0.016245</value>
    <value cell_id="158">-0.367651,0.055041,0.126921</value>
    <value cell_id="159">-0.481302,0.273821,0.294210</value>
    <value cell_id="160">-0.484529,0.078739,0.323202</value>
    <value cell_id="161">-0.368567,0.115709,0.088760</value>
    <value cell_id="162">-0.171870,0.165137,-0.044094</value>
    <value cell_id="163">-0.172824,-0.085886,0.160055</value>
    <value cell_id="164">-0.373219,0.129486,0.233190</value>
    <value cell_id="165">-0.491004,0.318238,0.124164</value>
    <value cell_id="166">-0.490010,0.089896,0.071238</value>
    <value cell_id="167">-0.369082,0.181687,0.132792</value>
    <value cell_id="168">-0.170777,0.220409,0.093596</value>
    <value cell_id="169">-0.126089,-0.089514,0.208684</value>
    <value cell_id="170">-0.277997,0.016706,0.294320</value>
    <value cell_id="171">-0.373379,0.205356,0.173779</value>
    <value cell_id="172">-0.373243,0.263424,0.119257</value>
    <value cell_id="173">-0.277704,0.349142,0.207119</value>
    <value cell_id="174">-0.126634,0.261275,0.162938</value>
    <value cell_id="175">-0.055850,-0.061658,0.128628</value>
    <value cell_id="176">-0.125399,-0.038846,0.207674</value>
    <value cell_id="177">-0.171802,0.084860,0.189210</value>
    <value cell_id="178">-0.172912,0.221965,0.170184</value>
    <value cell_id="179">-0.127842,0.270025,0.177404</value>
    <value cell_id="180">-0.057664,0.168502,0.113989</value>
    <value cell_id="181">-0.017870,0.045793,0.037649</value>
    <value cell_id="182">-0.037856,0.090809,0.130695</value>
    <value cell_id="183">-0.049723,0.086061,0.229659</value>
    <value cell_id="184">-0.049808,0.028348,0.241827</value>
    <value cell_id="185">-0.037841,-0.023654,0.151997</value>
    <value cell_id="186">-0.017743,-0.026130,0.048956</value>
    <value cell_id="187">-0.039503,0.145152,0.067619</value>
    <value cell_id="188">-0.081854,0.274089,0.228365</value>
    <value cell_id="189">-0.105437,0.223828,0.402683</value>
    <value cell_id="190">-0.105087,0.010081,0.433772</value>
    <value cell_id="191">-0.080420,-0.135386,0.276965</value>
    <value cell_id="192">-0.038133,-0.103125,0.090528</value>
    <value cell_id="193">-0.054519,0.236672,0.056920</value>
    <value cell_id="194">-0.111501,0.426770,0.159876</value>
    <value cell_id="195">-0.141358,0.298394,0.262634</value>
    <value cell_id="196">-0.139354,-0.081657,0.292611</value>
    <value cell_id="197">-0.106562,-0.288290,0.198992</value>
    <value cell_id="198">-0.050712,-0.188176,0.071167</value>
    <value cell_id="199">-0.056630,0.232756,0.014687</value>
    <value cell_id="200">-0.116505,0.396736,-0.025119</value>
    <value cell_id="201">-0.147486,0.227590,-0.097411</value>
    <value cell_id="202">-0.144064,-0.160567,-0.106524</value>
    <value cell_id="203">-0.108836,-0.329564,-0.044791</value>
    <value cell_id="204">-0.051230,-0.195645,-0.000446</value>
    <value cell_id="205">-0.043378,0.138220,-0.017678</value>
    <value cell_id="206">-0.091312,0.223955,-0.129680</value>
    <value cell_id="207">-0.117684,0.111428,-0.278939</value>
    <value cell_id="208">-0.114721,-0.115156,-0.306007</value>
    <value cell_id="209">-0.085094,-0.203413,-0.180485</value>
    <value cell_id="210">-0.039215,-0.116407,-0.048538</value>
    <value cell_id="211">-0.020098,0.042528,-0.017048</value>
    <value cell_id="212">-0.043367,0.065560,-0.088228</value>
    <value cell_id="213">-0.057126,0.030576,-0.176466</value>
    <value cell_id="214">-0.055943,-0.032772,-0.192929</value>
    <value cell_id="215">-0.040955,-0.057428,-0.119914</value>
    <value cell_id="216">-0.018516,-0.032849,-0.036319</value>
</field>
